MANIFEST.in
README.md
setup.py
mongo/__init__.py
mongo.egg-info/PKG-INFO
mongo.egg-info/SOURCES.txt
mongo.egg-info/dependency_links.txt
mongo.egg-info/top_level.txt