Metadata-Version: 1.1
Name: mongo
Version: 0.0.1
Summary: Minimalistic pymongo object wrapper
Home-page: https://github.com/imbolc/pongo
Author: Imbolc
Author-email: imbolc@imbolc.name
License: MIT License
Download-URL: https://github.com/imbolc/pongo/tarball/master
Keywords: mongodb,pymongo,orm
Platform: UNKNOWN
Classifier: Development Status :: 4 - Beta
Classifier: Intended Audience :: Developers
Classifier: Programming Language :: Python
Requires: pymongo
